{
  "sections": {
    "main": {
      "type": "main-page",
      "settings": {
        "padding_top": 28,
        "padding_bottom": 28
      }
    },
    "d80a8497-aeab-4bb3-b15b-711d40c97013": {
      "type": "multicolumn",
      "blocks": {
        "template--16981703000320__d80a8497-aeab-4bb3-b15b-711d40c97013-column-1": {
          "type": "column",
          "settings": {
            "title": "Animation",
            "text": "<p>Character creation and simple animation can help bring your explainer video or presentation to life. Our team is skilled with creating exactly these types of animations.<\/p>",
            "link_label": "Read More",
            "link": "shopify:\/\/pages\/animation-motion-graphics"
          }
        },
        "template--16981703000320__d80a8497-aeab-4bb3-b15b-711d40c97013-column-2": {
          "type": "column",
          "settings": {
            "title": "Motion Graphics",
            "text": "<p>Want to catch someone's attention, wow an audience, or simply have great looking on-screen graphics, motion graphics can help. <\/p>",
            "link_label": "Read More",
            "link": "shopify:\/\/pages\/animation-motion-graphics"
          }
        },
        "template--16981703000320__d80a8497-aeab-4bb3-b15b-711d40c97013-column-3": {
          "type": "column",
          "settings": {
            "title": "Video Editing",
            "text": "<p>Our video editors will work with you to develop and finalize any video project. This can be a project we started or one using your existing video and audio assets. <\/p>",
            "link_label": "Read More",
            "link": "shopify:\/\/pages\/video-editing"
          }
        },
        "ac702df4-6e54-46c8-8e83-46047660aad6": {
          "type": "column",
          "settings": {
            "title": "Video Production",
            "text": "<p>From production, to shooting, to sound, coordinating with professional talent, and finally mixing the final video, we are your one-stop-shop. <\/p>",
            "link_label": "Read More",
            "link": "shopify:\/\/pages\/video-production"
          }
        }
      },
      "block_order": [
        "template--16981703000320__d80a8497-aeab-4bb3-b15b-711d40c97013-column-1",
        "template--16981703000320__d80a8497-aeab-4bb3-b15b-711d40c97013-column-2",
        "template--16981703000320__d80a8497-aeab-4bb3-b15b-711d40c97013-column-3",
        "ac702df4-6e54-46c8-8e83-46047660aad6"
      ],
      "settings": {
        "title": "Our Services",
        "heading_size": "h1",
        "image_width": "full",
        "image_ratio": "adapt",
        "columns_desktop": 4,
        "column_alignment": "left",
        "background_style": "primary",
        "button_label": "Contact Us to Get Started",
        "button_link": "shopify:\/\/pages\/contact",
        "color_scheme": "scheme-1",
        "columns_mobile": "1",
        "swipe_on_mobile": false,
        "padding_top": 36,
        "padding_bottom": 36
      }
    },
    "60bc8b00-9db8-4711-a0e4-b0b8d03b9cd2": {
      "type": "rich-text",
      "blocks": {
        "template--16981696413952__60bc8b00-9db8-4711-a0e4-b0b8d03b9cd2-heading-1": {
          "type": "heading",
          "settings": {
            "heading": "Should I have videos for my business?",
            "heading_size": "h1"
          }
        },
        "template--16981696413952__60bc8b00-9db8-4711-a0e4-b0b8d03b9cd2-text-1": {
          "type": "text",
          "settings": {
            "text": "<p>Motion graphics is a technique that involves using computer-generated graphics and animation to create the illusion of motion or change. It is often used to create visual effects for video and film, as well as for television, online video, and other forms of digital media. Motion graphics can be used to enhance the visual appeal of a video or film by adding movement and visual interest to static graphics or images. It is also used to create interactive graphics for websites and other digital media.<\/p>"
          }
        }
      },
      "block_order": [
        "template--16981696413952__60bc8b00-9db8-4711-a0e4-b0b8d03b9cd2-heading-1",
        "template--16981696413952__60bc8b00-9db8-4711-a0e4-b0b8d03b9cd2-text-1"
      ],
      "settings": {
        "desktop_content_position": "center",
        "content_alignment": "left",
        "color_scheme": "",
        "full_width": true,
        "padding_top": 40,
        "padding_bottom": 52
      }
    },
    "fd306505-8e0d-472f-955e-936880dccfb3": {
      "type": "rich-text",
      "blocks": {
        "5ffe473d-c58f-4792-a0c2-7ed8bbd8a6b4": {
          "type": "heading",
          "settings": {
            "heading": "Are videos cost-effective for business marketing?",
            "heading_size": "h1"
          }
        },
        "5aba24a1-0ba4-43ab-a3b1-63827ef42fa2": {
          "type": "text",
          "settings": {
            "text": "<p>Videos can be an effective and cost-efficient way to promote your business, but the cost will depend on a number of factors, including the type of video you want to create, the length of the video, and the level of production value you want to achieve.<\/p><p>For example, a simple explainer video with animated graphics and a voiceover might cost a few hundred dollars to produce, while a more complex video with live action footage, special effects, and professional actors could cost thousands of dollars.<\/p><p>It's also important to consider the ongoing costs of hosting and promoting your videos. You may need to pay to host your videos on a platform like YouTube or Vimeo, and you may need to invest in advertising your videos on social media or through other channels in order to reach a larger audience.<\/p><p>Overall, it's a good idea to set a budget for your video marketing efforts and to consider the potential return on investment when deciding how much to spend.<\/p>"
          }
        }
      },
      "block_order": [
        "5ffe473d-c58f-4792-a0c2-7ed8bbd8a6b4",
        "5aba24a1-0ba4-43ab-a3b1-63827ef42fa2"
      ],
      "settings": {
        "desktop_content_position": "center",
        "content_alignment": "left",
        "color_scheme": "",
        "full_width": true,
        "padding_top": 40,
        "padding_bottom": 52
      }
    },
    "60913c22-e300-4e78-930f-26278c7bf9d6": {
      "type": "rich-text",
      "blocks": {
        "template--16981696413952__60913c22-e300-4e78-930f-26278c7bf9d6-heading-1": {
          "type": "heading",
          "settings": {
            "heading": "Ready to start your project?",
            "heading_size": "h1"
          }
        },
        "template--16981696413952__60913c22-e300-4e78-930f-26278c7bf9d6-button-1": {
          "type": "button",
          "settings": {
            "button_label": "Contact Us",
            "button_link": "shopify:\/\/pages\/contact",
            "button_style_secondary": false,
            "button_label_2": "",
            "button_link_2": "",
            "button_style_secondary_2": false
          }
        }
      },
      "block_order": [
        "template--16981696413952__60913c22-e300-4e78-930f-26278c7bf9d6-heading-1",
        "template--16981696413952__60913c22-e300-4e78-930f-26278c7bf9d6-button-1"
      ],
      "settings": {
        "desktop_content_position": "center",
        "content_alignment": "center",
        "color_scheme": "",
        "full_width": true,
        "padding_top": 40,
        "padding_bottom": 52
      }
    }
  },
  "order": [
    "main",
    "d80a8497-aeab-4bb3-b15b-711d40c97013",
    "60bc8b00-9db8-4711-a0e4-b0b8d03b9cd2",
    "fd306505-8e0d-472f-955e-936880dccfb3",
    "60913c22-e300-4e78-930f-26278c7bf9d6"
  ]
}
